{"code":0,"data":{"weaponId":10382,"weaponName":"加利尔轻机枪","weaponEnName":"","weaponType":"机枪","weaponBullet":"重型弹","weaponIcon":"https://community-cdn.exiliumgf.com/prod/1764333241014.png","weaponDesc":"攻击265【60级】","weaponTrait":"若造成范围伤害，则施加1个减益效果，持续1回合。","skills":[{"level":"慎行Lv.1","description":"若主动攻击时剩余行动力大于3格，则造成伤害提高5%。若目标拥有减益效果，则额外提高5%。"},{"level":"慎行Lv.2","description":"若主动攻击时剩余行动力大于3格，则造成伤害提高7%。若目标拥有减益效果，则额外提高5%。"},{"level":"慎行Lv.3","description":"若主动攻击时剩余行动力大于3格，则造成伤害提高9%。若目标拥有减益效果，则额外提高5%。"},{"level":"慎行Lv.4","description":"若主动攻击时剩余行动力大于3格，则造成伤害提高11%。若目标拥有减益效果，则额外提高5%。"},{"level":"慎行Lv.5","description":"若主动攻击时剩余行动力大于3格，则造成伤害提高13%。若目标拥有减益效果，则额外提高5%。"},{"level":"慎行Lv.6","description":"若主动攻击时剩余行动力大于3格，则造成伤害提高15%。若目标拥有减益效果，则额外提高5%。"}]},"msg":"成功"}