{"code":0,"data":[{"characterId":1034,"coreWeaponId":"10343","characterWeapon":"瓦尔特2000","characterName":"玛绮朵","characterEnName":"MAKIATTO","characterQuality":"精英人形","characterTeam":"方糖咖啡馆","characterModel":"SSD-62D","characterDesc":"冷凝狙击，单体高爆伤害，暴击率高但爆伤略低。有护盾和伏击，血量高时加射程。适合冷凝队打单体爆发。","characterRemarks":"冷静高傲、不善表达的别扭人形。喜欢毛绒绒的小动物，也喜欢糖分超标的玛奇朵。总是独来独往的她，目光却常常停留在某一处。到底什么时候，她才能获得想要的回应呢？","classType":1,"classIcon":"https://front.pangpangta.com/source/classtype/SENTINEL-BLACK.png","elementIcon":"https://front.pangpangta.com/source/element/Ice.png","attributes":{"attack":844,"stability":9,"defense":504,"actionPoints":4,"hp":1819},"image":{"imageArt":"https://gf2-cn.cdn.sunborngame.com/website/official_zf/pc/image2/ilus-MACQIATO_b934ef8f08.png","imageAvatar":"https://gf2-cn.cdn.sunborngame.com/website/official_zf/pc/image2/head-MACQIATO_bd683307fd.png","imagePanel":"https://gf2-cn.cdn.sunborngame.com/website/official_zf/pc/image2/allroles-roles-1034_b0c99de712.png","imageUpper":"https://gf2-cn.cdn.sunborngame.com/website/official_zf/pc/image2/roles-img-MACQIATO_a5ec0490b5.png"},"characterSkin":[{"id":40,"skin_name":"花影重","portrait_pc":"https://community-cdn.exiliumgf.com/prod/wiki/1763949940442.png","portrait_mobile":"https://community-cdn.exiliumgf.com/prod/wiki/1763949963399.png"},{"id":41,"skin_name":"舞会休止符","portrait_pc":"https://community-cdn.exiliumgf.com/prod/wiki/1763949976748.png","portrait_mobile":"https://community-cdn.exiliumgf.com/prod/wiki/1763949987879.png"},{"id":56,"skin_name":"汤风休日","portrait_pc":"https://community-cdn.exiliumgf.com/prod/wiki/1765097627679.png","portrait_mobile":"https://community-cdn.exiliumgf.com/prod/wiki/1765097618719.png"}],"imageGif":["https://community-cdn.exiliumgf.com/prod/wiki/1768262077184.gif","https://community-cdn.exiliumgf.com/prod/wiki/1768262088257.gif","https://community-cdn.exiliumgf.com/prod/wiki/1768262097208.gif"],"weakness":[{"title":"轻型弹","icon":"https://front.pangpangta.com/source/element/colorful/Icon_BulletHit_Light_Weakpoint.png"},{"title":"燃烧","icon":"https://front.pangpangta.com/source/element/Fire.png"}],"features":[{"title":"重型弹","icon":"https://front.pangpangta.com/source/element/colorful/Icon_BulletHit_Heavy_Weakpoint.png"},{"title":"冷凝","icon":"https://front.pangpangta.com/source/element/Ice.png"}],"weapons":[{"weaponId":10333,"weaponLevel":5},{"weaponId":10003,"weaponLevel":5}],"accessories":[{"packageId":9,"score":5,"commend":[{"title":"攻击"},{"title":"攻击加成"},{"title":"暴击"},{"title":"暴击伤害"}]}],"skills":[{"type":"普攻","skillName":"独狼领域","skillSummary":"普攻/精准","skillBullet":"","skillAttribute":"","skillIcon":"https://gf2.mcc.wiki/image/skill/Skill_Attack_SniperRifle.png","steadyState":2,"cooldown":null,"skills":[{"skillLevel":1,"skillDesc":"选取周围半径9格内的1个敌方目标，对其造成80%攻击力的物理伤害。","tooltips":[]}]},{"type":"主动","skillName":"冷厉闪狙","skillSummary":"主动/精准","skillBullet":"","skillAttribute":"","skillIcon":"https://gf2.mcc.wiki/image/skill/Skill_MacqiatoSSR_Active_2.png","steadyState":1,"cooldown":null,"skills":[{"skillLevel":1,"skillDesc":"选取周围半径9格内的1个敌方目标，对其造成160%攻击力的冷凝伤害。此次攻击暴击伤害提高30%。每造成一次伤害，获得1层必胜信念。","tooltips":[{"text":"必胜信念","content":"必胜信念:攻击力提高10%，至多叠加3层。使用主动技能冷厉闪狙之外的指令时消除。不可驱散。"}]}]},{"type":"主动","skillName":"专业手段","skillSummary":"主动/精准/增益","skillBullet":"","skillAttribute":"","skillIcon":"https://gf2.mcc.wiki/image/skill/Skill_MacqiatoSSR_Active_1.png","steadyState":2,"cooldown":null,"skills":[{"skillLevel":1,"skillDesc":"选取周围半径9格内的1个敌方目标，对其造成130%攻击力的物理伤害，获得4点导染指数，并获得2层常规策略。","tooltips":[{"text":"常规策略","content":"常规策略:受到的范围伤害降低25%，每受到1次范围伤害消耗1层，至多叠加3层。增益效果。"}]}]},{"type":"制胜","skillName":"绝对心防","skillSummary":"制胜/增益/伏击/减益","skillBullet":"","skillAttribute":"","skillIcon":"https://gf2.mcc.wiki/image/skill/Skill_MacqiatoSSR_Active_3.png","steadyState":null,"cooldown":null,"skills":[{"skillLevel":1,"skillDesc":"获得寒霜屏障和警戒，持续2回合，寒霜屏障吸收量为65%初始攻击力，至多不超过60%最大生命值。","tooltips":[{"text":"寒霜屏障","content":"寒霜屏障:寒霜屏障，寒霜屏障被击破时，对击破者施加警戒，持续1回合。冷凝类增益，不可驱散。"},{"text":"警戒","content":"警戒:寒霜屏障存在时，自身周围半径9格内的敌方单位主动攻击前，对其进行警戒，造成90%攻击力的冷凝伤害和2点稳态伤害，并施加{2}，持续1回合，每回合至多触发2次。不可驱散。"},{"text":"寒霜屏障","content":"寒霜屏障:寒霜屏障，寒霜屏障被击破时，对击破者施加警戒，持续1回合。冷凝类增益，不可驱散。"}]}]},{"type":"被动","skillName":"战场洞悉","skillSummary":"被动/增益","skillBullet":"","skillAttribute":"","skillIcon":"https://gf2.mcc.wiki/image/skill/Skill_MacqiatoSSR_Passive_4.png","steadyState":null,"cooldown":null,"skills":[{"skillLevel":1,"skillDesc":"暴击率提高40%，暴击伤害降低10%。 回合开始时，若自身生命值大于80%，则获得洞察和稳步行动，持续到下回合开始。 攻击拥有凝固的敌方目标时，无视4点稳态指数，对其造成伤害提高20%；攻击拥有僵冷的敌方目标时，无视6点稳态指数，且造成伤害提高30%；两种效果无法叠加。","tooltips":[{"text":"洞察","content":"洞察:制胜技能的射程增加1格。增益效果。"},{"text":"稳步行动","content":"稳步行动:行动力增加1格，免疫敌方单位施加的位移效果。不可驱散。"},{"text":"凝固","content":"凝固:行动力降低1格；行动结束时，若拥有2层凝固，则转化为洞察，持续1回合；至多叠加2层。冷凝类移动减益。"},{"text":"僵冷","content":"僵冷:无法移动、无法主动位移。冷凝类移动减益。"}]}]}],"battleSkill":[{"level":"椎体·一","skillLevel":"冷厉闪狙 Lv.2","effect":"进行两次攻击，暴击伤害不再提高，造成伤害降低至攻击力的100%。若第一次攻击产生暴击，则第二次攻击的暴击率提高100%，且暴击伤害提高80%。","extraEffect":"选取周围半径9格内的1个敌方目标，对其进行两次攻击，造成100%攻击力的冷凝伤害。每造成一次伤害，获得1层必胜信念。若第一次攻击产生暴击，则第二次攻击的暴击率提高100%，且暴击伤害提高80%。","tooltips":[{"text":"必胜信念","content":"必胜信念:攻击力提高10%，至多叠加3层。使用主动技能冷厉闪狙之外的指令时消除。不可驱散。"}]},{"level":"椎体·二","skillLevel":"绝对心防 Lv.2","effect":"寒霜屏障的吸收量增加为初始攻击力的80%，至多不超过80%最大生命值。每回合伏击的触发次数增加1次。","extraEffect":"获得寒霜屏障和警戒，持续2回合，寒霜屏障吸收量为80%初始攻击力，至多不超过80%最大生命值。","tooltips":[{"text":"寒霜屏障","content":"寒霜屏障:寒霜屏障，寒霜屏障被击破时，对击破者施加警戒，持续1回合。冷凝类增益，不可驱散。"},{"text":"警戒","content":"警戒:寒霜屏障存在时，自身周围半径9格内的敌方单位主动攻击前，对其进行警戒，造成90%攻击力的冷凝伤害和2点稳态伤害，并施加{2}，持续1回合，每回合至多触发3次。不可驱散。"}]},{"level":"椎体·三","skillLevel":"战场洞悉 Lv.2","effect":"对拥有凝固的敌方目标造成冷凝伤害时，无视的稳态指数提高至6点；对拥有僵冷的敌方目标造成冷凝伤害时，无视的稳态指数提高至10点。","extraEffect":"暴击率提高40%，暴击伤害降低10%。回合开始时，若自身生命值大于80%，则获得洞察和稳步行动，持续到下回合开始。攻击拥有凝固的敌方目标时，无视4点稳态指数，对其造成伤害提高20%，若造成冷凝伤害，无视的稳态指数提高至6点；攻击拥有僵冷的敌方目标时，无视6点稳态指数，且造成伤害提高30%，若造成冷凝伤害，无视的稳态指数提高至10点；两种效果无法叠加。","tooltips":[{"text":"凝固","content":"凝固:行动力降低1格；行动结束时，若拥有2层凝固，则转化为洞察，持续1回合；至多叠加2层。冷凝类移动减益。"},{"text":"僵冷","content":"僵冷:无法移动、无法主动位移。冷凝类移动减益。"},{"text":"洞察","content":"洞察:制胜技能的射程增加1格。增益效果。"},{"text":"稳步行动","content":"稳步行动:行动力增加1格，免疫敌方单位施加的位移效果。不可驱散。"}]},{"level":"椎体·四","skillLevel":"专业手段 Lv.2","effect":"常规策略修改为应急策略。","extraEffect":"选取周围半径9格内的1个敌方目标，对其造成130%攻击力的物理伤害，获得4点导染指数，并获得2层应急策略。","tooltips":[{"text":"常规策略","content":"常规策略:受到的范围伤害降低25%，每受到1次范围伤害消耗1层，至多叠加3层。增益效果。"},{"text":"应急策略","content":"应急策略:受到的范围伤害降低为当前层数×25%，每受到1次范围伤害消耗1层，至多叠加3层。增益效果。"}]},{"level":"椎体·五","skillLevel":"战场洞悉 Lv.3","effect":"对拥有凝固或僵冷的敌方目标造成冷凝伤害时，无视的稳态指数提高至10点，且造成伤害均提高30%。","extraEffect":"暴击率提高40%，暴击伤害降低10%。回合开始时，若自身生命值大于80%，则获得洞察和稳步行动，持续到下回合开始。攻击拥有凝固的敌方目标时，无视4点稳态指数，对其造成伤害提高20%；攻击拥有僵冷的敌方目标时，无视6点稳态指数，且造成伤害提高30%；对拥有凝固或僵冷的敌方目标造成冷凝伤害时，无视的稳态指数提高至10点，且造成伤害均提高30%。两种效果无法叠加。","tooltips":[{"text":"凝固","content":"凝固:行动力降低1格；行动结束时，若拥有2层凝固，则转化为洞察，持续1回合；至多叠加2层。冷凝类移动减益。"},{"text":"僵冷","content":"僵冷:无法移动、无法主动位移。冷凝类移动减益。"},{"text":"洞察","content":"洞察:制胜技能的射程增加1格。增益效果。"},{"text":"稳步行动","content":"稳步行动:行动力增加1格，免疫敌方单位施加的位移效果。不可驱散。"}]},{"level":"椎体·六","skillLevel":"绝对心防 Lv.3","effect":"施放绝对心防后，每次行动结束时，获得2点导染指数，生效2次。每回合伏击的触发次数增加1次。伏击暴击后，获得加倍专注，持续1回合。","extraEffect":"获得寒霜屏障和警戒，持续2回合，寒霜屏障吸收量为80%初始攻击力，至多不超过80%最大生命值。施放该技能后，每次行动结束时，获得2点导染指数，生效2次。","tooltips":[{"text":"加倍专注","content":"加倍专注:造成伤害提高7.5%，至多叠加4层。不可驱散。"},{"text":"寒霜屏障","content":"寒霜屏障:寒霜屏障，寒霜屏障被击破时，对击破者施加警戒，持续1回合。冷凝类增益，不可驱散。"},{"text":"警戒","content":"警戒:寒霜屏障存在时，自身周围半径9格内的敌方单位主动攻击前，对其进行警戒，造成90%攻击力的冷凝伤害和2点稳态伤害，并施加加倍专注，持续1回合，每回合至多触发4次。警戒暴击后，获得{3}，持续1回合。不可驱散。"}]}],"commendKeys":["10237","10337","10347","10341","10342","10346"],"characterKeys":[{"keyId":"10340","keyType":"契合键","keyName":"焦糖心意","keyIcon":"https://gf2.mcc.wiki/image/key/Skill_Chrtalent_MacqiatoSSR_love.png","keyDesc":"","keyParam":"攻击加成3% 生命加成3% 暴击伤害3%  "},{"keyId":"10341","keyType":"固键","keyName":"附加情报","keyIcon":"https://gf2.mcc.wiki/image/key/Skill_Chrtalent_Macqiato01.png","keyDesc":"主动技能冷厉闪狙造成击杀时，获得1点导染指数。","keyParam":""},{"keyId":"10342","keyType":"固键","keyName":"加冰加奶沫","keyIcon":"https://gf2.mcc.wiki/image/key/Skill_Chrtalent_Macqiato02.png","keyDesc":"战斗开始时获得3点导染指数。","keyParam":""},{"keyId":"10343","keyType":"固键","keyName":"不屈独狼","keyIcon":"https://gf2.mcc.wiki/image/key/Skill_Chrtalent_Macqiato03.png","keyDesc":"施放主动技能专业手段后，若自身周围半径3格内没有其他友方单位，则获得1层独狼。","keyParam":""},{"keyId":"10344","keyType":"固键","keyName":"休整时机","keyIcon":"https://gf2.mcc.wiki/image/key/Skill_Chrtalent_Macqiato04.png","keyDesc":"在冷凝地格上施放独狼领域、冷厉闪狙或专业手段后，驱散自身身上所有冷凝类减益效果，并获得3格移动追加。","keyParam":""},{"keyId":"10345","keyType":"固键","keyName":"加热加焦糖","keyIcon":"https://gf2.mcc.wiki/image/key/Skill_Chrtalent_Macqiato05.png","keyDesc":"战斗开始时，对全场生命值最高的敌方单位施加颤栗杀机。","keyParam":""},{"keyId":"10346","keyType":"固键","keyName":"绝对专注","keyIcon":"https://gf2.mcc.wiki/image/key/Skill_Chrtalent_Macqiato06.png","keyDesc":"战斗开始时，攻击力提高10%，持续到生命值首次低于100%。","keyParam":""},{"keyId":"10347","keyType":"共键","keyName":"生存本能","keyIcon":"https://gf2.mcc.wiki/image/key/Skill_Chrtalent_MacqiatoSSR.png","keyDesc":"行动开始时，若自身生命值大于80%，则受到攻击时，受到的稳态伤害降低2点，每回合至多生效1次。","keyParam":"攻击加成5%  "},{"keyId":"10348","keyType":"跃键","keyName":"狙心锁定","keyIcon":"https://gf2.mcc.wiki/image/key/Skill_Chrtalent_MacqiatoSSR_expand.png","keyDesc":"伏击造成的暴击伤害提高30%。 使用制胜技能绝对心防后，获得指令追加，且当前回合内返还主动技能冷厉闪狙消耗的导染指数，攻击首领单位前，对其施加糖分过量，持续2回合。","keyParam":""}],"flowers":["1","1","1","1","2","2"],"mimicry":[{"level":"胚胎","unlockLevel":0,"materials":["尖兵*2火力*5"],"effect":"伏击 造成的伤害提高 8% 。"},{"level":"幼苗","unlockLevel":10,"materials":["尖兵*3火力*8"],"effect":"受到的物理和异位伤害降低 5% 。"},{"level":"花芽","unlockLevel":20,"materials":["防卫*1尖兵*4火力*9"],"effect":"造成的 冷凝伤害 提高 5% 。"},{"level":"花蕾","unlockLevel":30,"materials":["防卫*2尖兵*6火力*11"],"effect":"对稳态崩溃的敌方单位造成的伤害提高 10% 。"},{"level":"花苞","unlockLevel":45,"materials":["防卫*2尖兵*7火力*15"],"effect":"攻击力提高 8% 。"},{"level":"花朵","unlockLevel":60,"materials":["防卫*3尖兵*8火力*18"],"effect":"对自身 周围半径5格外 的敌方单位造成的伤害提高 12% 。"}],"teams":[],"reference":["https://gf2-bbs.exiliumgf.com/threadInfo?id=121&hash_flag=2","https://gf2-bbs.exiliumgf.com/threadInfo?id=88&hash_flag=2"]}],"msg":"成功"}