{
  "Code": 0,
  "Message": "OK",
  "data": {
    "can_modify": false,
    "info": {
      "hero_id": 10131,
      "name": "旧式通用冲锋枪9",
      "view_num": 21,
      "update_time": "",
      "base_info": "<table style=\"border-collapse: collapse; width: 99.9391%; height: 310px; margin-left: auto; margin-right: auto;\" border=\"1\">\n<tbody>\n<tr style=\"height: 200px;\">\n<td style=\"width: 99.9391%; height: 101px;\" colspan=\"2\"><span style=\"color: #ffffff;\"><img style=\"display: block; margin-left: auto; margin-right: auto;\" src=\"https://community-cdn.exiliumgf.com/prod/1764402412541.png\" width=\"400\" height=\"200\" /></span></td>\n</tr>\n<tr style=\"height: 50px;\">\n<td class=\"xl65\" style=\"width: 18.1597%; height: 50px; text-align: center;\" width=\"137\" height=\"23\"><span style=\"color: #ffffff;\">武器名</span></td>\n<td class=\"xl66\" style=\"height: 16.5pt; width: 81.7794%; text-align: center;\" width=\"1571\" height=\"22\"><span style=\"color: #ffffff;\">旧式通用冲锋枪9</span></td>\n</tr>\n<tr style=\"height: 50px; text-align: center;\">\n<td class=\"xl66\" style=\"border-top: none; width: 18.1597%; text-align: center; height: 50px;\" height=\"23\"><span style=\"color: #ffffff;\">属性</span></td>\n<td class=\"xl65\" style=\"height: 16.5pt; border-top: none; width: 81.7794%; text-align: center;\" height=\"22\"><span style=\"color: #ffffff;\">攻击153【60级】</span></td>\n</tr>\n</tbody>\n</table>",
      "character": "<table style=\"border-collapse: collapse; width: 99.954%; margin-left: auto; margin-right: auto;\" border=\"1\">\n<tbody>\n<tr style=\"height: 16.5pt;\">\n<td class=\"xl63\" style=\"width: 24.3754%; height: 60px; text-align: center;\" width=\"137\" height=\"22\"><span style=\"color: #ffffff;\">火力武装Lv.1</span></td>\n<td class=\"xl65\" style=\"width: 75.5786%; height: 60px;\" width=\"1571\" height=\"22\"><span style=\"color: #ffffff;\">造成伤害提高1%。</span></td>\n</tr>\n<tr style=\"height: 16.5pt;\">\n<td class=\"xl64\" style=\"border-top: none; width: 24.3754%; height: 60px; text-align: center;\" height=\"22\"><span style=\"color: #ffffff;\">火力武装Lv.2</span></td>\n<td class=\"xl66\" style=\"border-top: none; width: 75.5786%; height: 60px;\" height=\"22\"><span style=\"color: #ffffff;\">造成伤害提高2%。</span></td>\n</tr>\n<tr style=\"height: 16.5pt;\">\n<td class=\"xl63\" style=\"border-top: none; width: 24.3754%; height: 60px; text-align: center;\" height=\"22\"><span style=\"color: #ffffff;\">火力武装Lv.3</span></td>\n<td class=\"xl65\" style=\"border-top: none; width: 75.5786%; height: 60px;\" height=\"22\"><span style=\"color: #ffffff;\">造成伤害提高3%。</span></td>\n</tr>\n<tr style=\"height: 16.5pt;\">\n<td class=\"xl64\" style=\"border-top: none; width: 24.3754%; height: 60px; text-align: center;\" height=\"22\"><span style=\"color: #ffffff;\">火力武装Lv.4</span></td>\n<td class=\"xl66\" style=\"border-top: none; width: 75.5786%; height: 60px;\" height=\"22\"><span style=\"color: #ffffff;\">造成伤害提高4%。</span></td>\n</tr>\n<tr style=\"height: 16.5pt;\">\n<td class=\"xl63\" style=\"border-top: none; width: 24.3754%; height: 60px; text-align: center;\" height=\"22\"><span style=\"color: #ffffff;\">火力武装Lv.5</span></td>\n<td class=\"xl65\" style=\"border-top: none; width: 75.5786%; height: 60px;\" height=\"22\"><span style=\"color: #ffffff;\">造成伤害提高5%。</span></td>\n</tr>\n<tr style=\"height: 16.5pt;\">\n<td class=\"xl64\" style=\"border-top: none; width: 24.3754%; height: 60px; text-align: center;\" height=\"22\"><span style=\"color: #ffffff;\">火力武装Lv.6</span></td>\n<td class=\"xl66\" style=\"border-top: none; width: 75.5786%; height: 60px;\" height=\"22\"><span style=\"color: #ffffff;\">造成伤害提高6%。</span></td>\n</tr>\n</tbody>\n</table>"
    }
  }
}
